{
    "quotes": [
        {
            "text": "My nana used to say today is a great day for a great day",
            "author": "John Nolan"
        },
        {
            "text": "Get that woman out of your house",
            "author": "Wade Grey"
        },
        {
            "text": "I thought Charlie was a guy",
            "author": "Angela Lopez"
        },
        {
            "text": "Rookie day is christmas and the purge in one",
            "author": "Timothy Bradford"
        },
        {
            "text": "Don’t make me pull the \"buried alive\" card",
            "author": "Lucy Chen"
        },
        {
            "text": "The only way to show you I'm a good cop is to show you I'm a good cop",
            "author": "Angela Lopez"
        },
        {
            "text": "I would shut that down so fast",
            "author": "Celina Juarez"
        },
        {
            "text": "In my mind, I'm hitting you right now",
            "author":"Lucy Chen"
        }
    ]
}